django_starterkit-1.0.4.dist-info/DESCRIPTION.rst
django_starterkit-1.0.4.dist-info/METADATA
django_starterkit-1.0.4.dist-info/RECORD
django_starterkit-1.0.4.dist-info/WHEEL
django_starterkit-1.0.4.dist-info/metadata.json
django_starterkit-1.0.4.dist-info/top_level.txt
sample_project/__init__.py
sample_project/settings.py
sample_project/urls.py
sample_project/wsgi.py
starterkit/__init__.py
starterkit/admin.py
starterkit/apps.py
starterkit/models.py
starterkit/password_validation.py
starterkit/utils.py
starterkit/auth/__init__.py
starterkit/auth/backends.py
starterkit/drf/__init__.py
starterkit/drf/permissions.py
starterkit/drf/validation.py
starterkit/migrations/__init__.py
tests/__init__.py
tests/runtests.py
tests/test_auth_backends.py
tests/test_drf_validation.py
tests/test_password_validation.py
tests/test_permissions.py
tests/test_utils.py
tests/urls.py
